{
	"$schema": "http://schema.management.azure.com/schemas/2015-01-01/deploymentTemplate.json#",
	"contentVersion": "1.0.0.0",
	"parameters": {
		"factoryName": {
			"type": "string",
			"metadata": "Data Factory name",
			"defaultValue": "adf-investment-funds"
		},
		"AzureFunction_ls_functionKey": {
			"type": "secureString",
			"metadata": "Secure string for 'functionKey' of 'AzureFunction_ls'"
		},
		"ls_azure_databricks_actual_quotes_http_accessToken": {
			"type": "secureString",
			"metadata": "Secure string for 'accessToken' of 'ls_azure_databricks_actual_quotes_http'"
		},
		"ls_cvm_if_adls_accountKey": {
			"type": "secureString",
			"metadata": "Secure string for 'accountKey' of 'ls_cvm_if_adls'"
		},
		"ls_sql_investiment_funds_db_connectionString": {
			"type": "secureString",
			"metadata": "Secure string for 'connectionString' of 'ls_sql_investiment_funds_db'"
		},
		"AzureFunction_ls_properties_typeProperties_functionAppUrl": {
			"type": "string",
			"defaultValue": "https://getsourcefilescvm.azurewebsites.net"
		},
		"AzureKeyVault_properties_typeProperties_baseUrl": {
			"type": "string",
			"defaultValue": "https://investimentFundsKV.vault.azure.net/"
		},
		"ls_cvm_if_adls_properties_typeProperties_url": {
			"type": "string",
			"defaultValue": "https://investimentfundsadls.dfs.core.windows.net/"
		},
		"ls_cvm_if_http_properties_typeProperties_url": {
			"type": "string",
			"defaultValue": "https://dados.cvm.gov.br/dados/FI/DOC/INF_DIARIO/DADOS/"
		},
		"ls_cvm_if_register_http_properties_typeProperties_url": {
			"type": "string",
			"defaultValue": "https://dados.cvm.gov.br/"
		}
	},
	"variables": {
		"factoryId": "[concat('Microsoft.DataFactory/factories/', parameters('factoryName'))]"
	},
	"resources": [
		{
			"name": "[concat(parameters('factoryName'), '/AzureFunction_ls')]",
			"type": "Microsoft.DataFactory/factories/linkedServices",
			"apiVersion": "2018-06-01",
			"properties": {
				"annotations": [],
				"type": "AzureFunction",
				"typeProperties": {
					"functionAppUrl": "[parameters('AzureFunction_ls_properties_typeProperties_functionAppUrl')]",
					"authentication": "Anonymous",
					"functionKey": {
						"type": "SecureString",
						"value": "[parameters('AzureFunction_ls_functionKey')]"
					}
				}
			},
			"dependsOn": []
		},
		{
			"name": "[concat(parameters('factoryName'), '/AzureKeyVault')]",
			"type": "Microsoft.DataFactory/factories/linkedServices",
			"apiVersion": "2018-06-01",
			"properties": {
				"annotations": [],
				"type": "AzureKeyVault",
				"typeProperties": {
					"baseUrl": "[parameters('AzureKeyVault_properties_typeProperties_baseUrl')]"
				}
			},
			"dependsOn": []
		},
		{
			"name": "[concat(parameters('factoryName'), '/ls_azure_databricks_actual_quotes_http')]",
			"type": "Microsoft.DataFactory/factories/linkedServices",
			"apiVersion": "2018-06-01",
			"properties": {
				"annotations": [],
				"type": "AzureDatabricks",
				"typeProperties": {
					"domain": "https://adb-4375646200372583.3.azuredatabricks.net",
					"accessToken": {
						"type": "SecureString",
						"value": "[parameters('ls_azure_databricks_actual_quotes_http_accessToken')]"
					},
					"newClusterNodeType": "Standard_DS3_v2",
					"newClusterNumOfWorker": "1",
					"newClusterSparkEnvVars": {
						"PYSPARK_PYTHON": "/databricks/python3/bin/python3"
					},
					"newClusterVersion": "14.3.x-cpu-ml-scala2.12",
					"newClusterDriverNodeType": "Standard_DS3_v2",
					"clusterOption": "Fixed",
					"newClusterInitScripts": []
				}
			},
			"dependsOn": []
		},
		{
			"name": "[concat(parameters('factoryName'), '/ls_cvm_if_adls')]",
			"type": "Microsoft.DataFactory/factories/linkedServices",
			"apiVersion": "2018-06-01",
			"properties": {
				"annotations": [],
				"type": "AzureBlobFS",
				"typeProperties": {
					"url": "[parameters('ls_cvm_if_adls_properties_typeProperties_url')]",
					"accountKey": {
						"type": "SecureString",
						"value": "[parameters('ls_cvm_if_adls_accountKey')]"
					}
				}
			},
			"dependsOn": []
		},
		{
			"name": "[concat(parameters('factoryName'), '/ls_cvm_if_http')]",
			"type": "Microsoft.DataFactory/factories/linkedServices",
			"apiVersion": "2018-06-01",
			"properties": {
				"annotations": [],
				"type": "HttpServer",
				"typeProperties": {
					"url": "[parameters('ls_cvm_if_http_properties_typeProperties_url')]",
					"enableServerCertificateValidation": true,
					"authenticationType": "Anonymous"
				}
			},
			"dependsOn": []
		},
		{
			"name": "[concat(parameters('factoryName'), '/ls_cvm_if_register_http')]",
			"type": "Microsoft.DataFactory/factories/linkedServices",
			"apiVersion": "2018-06-01",
			"properties": {
				"annotations": [],
				"type": "HttpServer",
				"typeProperties": {
					"url": "[parameters('ls_cvm_if_register_http_properties_typeProperties_url')]",
					"enableServerCertificateValidation": false,
					"authenticationType": "Anonymous"
				}
			},
			"dependsOn": []
		},
		{
			"name": "[concat(parameters('factoryName'), '/ls_sql_investiment_funds_db')]",
			"type": "Microsoft.DataFactory/factories/linkedServices",
			"apiVersion": "2018-06-01",
			"properties": {
				"annotations": [],
				"type": "AzureSqlDatabase",
				"typeProperties": {
					"connectionString": "[parameters('ls_sql_investiment_funds_db_connectionString')]"
				}
			},
			"dependsOn": []
		},
		{
			"name": "[concat(parameters('factoryName'), '/tr_daily_if_quotes')]",
			"type": "Microsoft.DataFactory/factories/triggers",
			"apiVersion": "2018-06-01",
			"properties": {
				"annotations": [],
				"runtimeState": "Stopped",
				"pipelines": [],
				"type": "ScheduleTrigger",
				"typeProperties": {
					"recurrence": {
						"frequency": "Week",
						"interval": 1,
						"startTime": "2024-08-13T23:36:00",
						"timeZone": "Bahia Standard Time",
						"schedule": {}
					}
				}
			},
			"dependsOn": []
		},
		{
			"name": "[concat(parameters('factoryName'), '/ds_cvm_actual_quotes_links')]",
			"type": "Microsoft.DataFactory/factories/datasets",
			"apiVersion": "2018-06-01",
			"properties": {
				"linkedServiceName": {
					"referenceName": "ls_cvm_if_adls",
					"type": "LinkedServiceReference"
				},
				"annotations": [],
				"type": "DelimitedText",
				"typeProperties": {
					"location": {
						"type": "AzureBlobFSLocation",
						"fileName": "cvm_actual_links.csv",
						"fileSystem": "raw"
					},
					"columnDelimiter": ",",
					"escapeChar": "\\",
					"firstRowAsHeader": true,
					"quoteChar": "\""
				},
				"schema": []
			},
			"dependsOn": [
				"[concat(variables('factoryId'), '/linkedServices/ls_cvm_if_adls')]"
			]
		},
		{
			"name": "[concat(parameters('factoryName'), '/ds_cvm_funds_register_adls')]",
			"type": "Microsoft.DataFactory/factories/datasets",
			"apiVersion": "2018-06-01",
			"properties": {
				"linkedServiceName": {
					"referenceName": "ls_cvm_if_adls",
					"type": "LinkedServiceReference"
				},
				"annotations": [],
				"type": "DelimitedText",
				"typeProperties": {
					"location": {
						"type": "AzureBlobFSLocation",
						"fileName": "register_fi.csv",
						"folderPath": "investment-funds-register",
						"fileSystem": "raw"
					},
					"columnDelimiter": ";",
					"escapeChar": "\\",
					"firstRowAsHeader": true,
					"quoteChar": "\""
				},
				"schema": [
					{
						"name": "TP_FUNDO",
						"type": "String"
					},
					{
						"name": "CNPJ_FUNDO",
						"type": "String"
					},
					{
						"name": "DENOM_SOCIAL",
						"type": "String"
					},
					{
						"name": "DT_REG",
						"type": "String"
					},
					{
						"name": "DT_CONST",
						"type": "String"
					},
					{
						"name": "CD_CVM",
						"type": "String"
					},
					{
						"name": "DT_CANCEL",
						"type": "String"
					},
					{
						"name": "SIT",
						"type": "String"
					},
					{
						"name": "DT_INI_SIT",
						"type": "String"
					},
					{
						"name": "DT_INI_ATIV",
						"type": "String"
					},
					{
						"name": "DT_INI_EXERC",
						"type": "String"
					},
					{
						"name": "DT_FIM_EXERC",
						"type": "String"
					},
					{
						"name": "CLASSE",
						"type": "String"
					},
					{
						"name": "DT_INI_CLASSE",
						"type": "String"
					},
					{
						"name": "RENTAB_FUNDO",
						"type": "String"
					},
					{
						"name": "CONDOM",
						"type": "String"
					},
					{
						"name": "FUNDO_COTAS",
						"type": "String"
					},
					{
						"name": "FUNDO_EXCLUSIVO",
						"type": "String"
					},
					{
						"name": "TRIB_LPRAZO",
						"type": "String"
					},
					{
						"name": "PUBLICO_ALVO",
						"type": "String"
					},
					{
						"name": "ENTID_INVEST",
						"type": "String"
					},
					{
						"name": "TAXA_PERFM",
						"type": "String"
					},
					{
						"name": "INF_TAXA_PERFM",
						"type": "String"
					},
					{
						"name": "TAXA_ADM",
						"type": "String"
					},
					{
						"name": "INF_TAXA_ADM",
						"type": "String"
					},
					{
						"name": "VL_PATRIM_LIQ",
						"type": "String"
					},
					{
						"name": "DT_PATRIM_LIQ",
						"type": "String"
					},
					{
						"name": "DIRETOR",
						"type": "String"
					},
					{
						"name": "CNPJ_ADMIN",
						"type": "String"
					},
					{
						"name": "ADMIN",
						"type": "String"
					},
					{
						"name": "PF_PJ_GESTOR",
						"type": "String"
					},
					{
						"name": "CPF_CNPJ_GESTOR",
						"type": "String"
					},
					{
						"name": "GESTOR",
						"type": "String"
					},
					{
						"name": "CNPJ_AUDITOR",
						"type": "String"
					},
					{
						"name": "AUDITOR",
						"type": "String"
					},
					{
						"name": "CNPJ_CUSTODIANTE",
						"type": "String"
					},
					{
						"name": "CUSTODIANTE",
						"type": "String"
					},
					{
						"name": "CNPJ_CONTROLADOR",
						"type": "String"
					},
					{
						"name": "CONTROLADOR",
						"type": "String"
					},
					{
						"name": "INVEST_CEMPR_EXTER",
						"type": "String"
					},
					{
						"name": "CLASSE_ANBIMA",
						"type": "String"
					}
				]
			},
			"dependsOn": [
				"[concat(variables('factoryId'), '/linkedServices/ls_cvm_if_adls')]"
			]
		},
		{
			"name": "[concat(parameters('factoryName'), '/ds_cvm_historic_source_binary_http')]",
			"type": "Microsoft.DataFactory/factories/datasets",
			"apiVersion": "2018-06-01",
			"properties": {
				"linkedServiceName": {
					"referenceName": "ls_cvm_if_http",
					"type": "LinkedServiceReference"
				},
				"parameters": {
					"relativeURL": {
						"type": "string"
					}
				},
				"annotations": [],
				"type": "Binary",
				"typeProperties": {
					"location": {
						"type": "HttpServerLocation",
						"relativeUrl": {
							"value": "@concat('HIST/',dataset().relativeURL)",
							"type": "Expression"
						}
					}
				}
			},
			"dependsOn": [
				"[concat(variables('factoryId'), '/linkedServices/ls_cvm_if_http')]"
			]
		},
		{
			"name": "[concat(parameters('factoryName'), '/ds_cvm_if_csv_adls')]",
			"type": "Microsoft.DataFactory/factories/datasets",
			"apiVersion": "2018-06-01",
			"properties": {
				"linkedServiceName": {
					"referenceName": "ls_cvm_if_adls",
					"type": "LinkedServiceReference"
				},
				"parameters": {
					"fileName": {
						"type": "string"
					},
					"raw_folder": {
						"type": "string"
					}
				},
				"annotations": [],
				"type": "DelimitedText",
				"typeProperties": {
					"location": {
						"type": "AzureBlobFSLocation",
						"fileName": {
							"value": "@dataset().fileName",
							"type": "Expression"
						},
						"folderPath": {
							"value": "@dataset().raw_folder",
							"type": "Expression"
						},
						"fileSystem": "raw"
					},
					"columnDelimiter": ";",
					"escapeChar": "\\",
					"firstRowAsHeader": true,
					"quoteChar": "\""
				},
				"schema": []
			},
			"dependsOn": [
				"[concat(variables('factoryId'), '/linkedServices/ls_cvm_if_adls')]"
			]
		},
		{
			"name": "[concat(parameters('factoryName'), '/ds_cvm_if_historic_quotes_links')]",
			"type": "Microsoft.DataFactory/factories/datasets",
			"apiVersion": "2018-06-01",
			"properties": {
				"linkedServiceName": {
					"referenceName": "ls_cvm_if_adls",
					"type": "LinkedServiceReference"
				},
				"annotations": [],
				"type": "DelimitedText",
				"typeProperties": {
					"location": {
						"type": "AzureBlobFSLocation"
					},
					"columnDelimiter": ",",
					"escapeChar": "\\",
					"firstRowAsHeader": true,
					"quoteChar": "\""
				},
				"schema": []
			},
			"dependsOn": [
				"[concat(variables('factoryId'), '/linkedServices/ls_cvm_if_adls')]"
			]
		},
		{
			"name": "[concat(parameters('factoryName'), '/ds_cvm_if_json_adls')]",
			"type": "Microsoft.DataFactory/factories/datasets",
			"apiVersion": "2018-06-01",
			"properties": {
				"linkedServiceName": {
					"referenceName": "ls_cvm_if_adls",
					"type": "LinkedServiceReference"
				},
				"annotations": [],
				"type": "Json",
				"typeProperties": {
					"location": {
						"type": "AzureBlobFSLocation",
						"fileName": "links.json",
						"fileSystem": "raw"
					}
				},
				"schema": {}
			},
			"dependsOn": [
				"[concat(variables('factoryId'), '/linkedServices/ls_cvm_if_adls')]"
			]
		},
		{
			"name": "[concat(parameters('factoryName'), '/ds_cvm_if_links_binary_adls')]",
			"type": "Microsoft.DataFactory/factories/datasets",
			"apiVersion": "2018-06-01",
			"properties": {
				"linkedServiceName": {
					"referenceName": "ls_cvm_if_adls",
					"type": "LinkedServiceReference"
				},
				"parameters": {
					"relativeURL": {
						"type": "string"
					}
				},
				"annotations": [],
				"type": "Binary",
				"typeProperties": {
					"location": {
						"type": "AzureBlobFSLocation",
						"fileName": {
							"value": "@dataset().relativeURL",
							"type": "Expression"
						},
						"folderPath": "staging",
						"fileSystem": "binary"
					},
					"compression": {
						"type": "ZipDeflate",
						"level": "Optimal"
					}
				}
			},
			"dependsOn": [
				"[concat(variables('factoryId'), '/linkedServices/ls_cvm_if_adls')]"
			]
		},
		{
			"name": "[concat(parameters('factoryName'), '/ds_cvm_if_links_binary_http')]",
			"type": "Microsoft.DataFactory/factories/datasets",
			"apiVersion": "2018-06-01",
			"properties": {
				"linkedServiceName": {
					"referenceName": "ls_cvm_if_http",
					"type": "LinkedServiceReference"
				},
				"parameters": {
					"relativeURL": {
						"type": "string"
					}
				},
				"annotations": [],
				"type": "Binary",
				"typeProperties": {
					"location": {
						"type": "HttpServerLocation",
						"relativeUrl": {
							"value": "@dataset().relativeURL",
							"type": "Expression"
						}
					},
					"compression": {
						"type": "ZipDeflate",
						"level": "Optimal"
					}
				}
			},
			"dependsOn": [
				"[concat(variables('factoryId'), '/linkedServices/ls_cvm_if_http')]"
			]
		},
		{
			"name": "[concat(parameters('factoryName'), '/ds_cvm_if_links_csv_adls')]",
			"type": "Microsoft.DataFactory/factories/datasets",
			"apiVersion": "2018-06-01",
			"properties": {
				"linkedServiceName": {
					"referenceName": "ls_cvm_if_adls",
					"type": "LinkedServiceReference"
				},
				"parameters": {
					"relativeURL": {
						"type": "string"
					}
				},
				"annotations": [],
				"type": "DelimitedText",
				"typeProperties": {
					"location": {
						"type": "AzureBlobFSLocation",
						"fileName": {
							"value": "@dataset().relativeURL",
							"type": "Expression"
						},
						"fileSystem": "teste"
					},
					"columnDelimiter": ",",
					"escapeChar": "\\",
					"firstRowAsHeader": true,
					"quoteChar": "\""
				},
				"schema": []
			},
			"dependsOn": [
				"[concat(variables('factoryId'), '/linkedServices/ls_cvm_if_adls')]"
			]
		},
		{
			"name": "[concat(parameters('factoryName'), '/ds_cvm_if_links_csv_http')]",
			"type": "Microsoft.DataFactory/factories/datasets",
			"apiVersion": "2018-06-01",
			"properties": {
				"linkedServiceName": {
					"referenceName": "ls_cvm_if_http",
					"type": "LinkedServiceReference"
				},
				"parameters": {
					"relativeUrl": {
						"type": "string"
					}
				},
				"annotations": [],
				"type": "DelimitedText",
				"typeProperties": {
					"location": {
						"type": "HttpServerLocation",
						"relativeUrl": {
							"value": "@dataset().relativeUrl",
							"type": "Expression"
						}
					},
					"columnDelimiter": ",",
					"compressionCodec": "ZipDeflate",
					"compressionLevel": "Optimal",
					"escapeChar": "\\",
					"firstRowAsHeader": true,
					"quoteChar": "\""
				},
				"schema": []
			},
			"dependsOn": [
				"[concat(variables('factoryId'), '/linkedServices/ls_cvm_if_http')]"
			]
		},
		{
			"name": "[concat(parameters('factoryName'), '/ds_cvm_if_register_adls')]",
			"type": "Microsoft.DataFactory/factories/datasets",
			"apiVersion": "2018-06-01",
			"properties": {
				"linkedServiceName": {
					"referenceName": "ls_cvm_if_adls",
					"type": "LinkedServiceReference"
				},
				"annotations": [],
				"type": "DelimitedText",
				"typeProperties": {
					"location": {
						"type": "AzureBlobFSLocation",
						"fileName": "register_fi.csv",
						"folderPath": "investment-funds-register",
						"fileSystem": "raw"
					},
					"columnDelimiter": ";",
					"escapeChar": "\\",
					"firstRowAsHeader": true,
					"quoteChar": "\""
				},
				"schema": []
			},
			"dependsOn": [
				"[concat(variables('factoryId'), '/linkedServices/ls_cvm_if_adls')]"
			]
		},
		{
			"name": "[concat(parameters('factoryName'), '/ds_cvm_if_register_http')]",
			"type": "Microsoft.DataFactory/factories/datasets",
			"apiVersion": "2018-06-01",
			"properties": {
				"linkedServiceName": {
					"referenceName": "ls_cvm_if_register_http",
					"type": "LinkedServiceReference"
				},
				"annotations": [],
				"type": "DelimitedText",
				"typeProperties": {
					"location": {
						"type": "HttpServerLocation",
						"relativeUrl": "dados/FI/CAD/DADOS/cad_fi.csv"
					},
					"columnDelimiter": ";",
					"escapeChar": "\\",
					"firstRowAsHeader": true,
					"quoteChar": "\""
				},
				"schema": []
			},
			"dependsOn": [
				"[concat(variables('factoryId'), '/linkedServices/ls_cvm_if_register_http')]"
			]
		}
	]
}